LICENSE
MANIFEST.in
README.md
pyproject.toml
setup.cfg
setup.py
src/nexradutils/__init__.py
src/nexradutils/download.py
src/nexradutils/io.py
src/nexradutils/plot.py
src/nexradutils.egg-info/PKG-INFO
src/nexradutils.egg-info/SOURCES.txt
src/nexradutils.egg-info/dependency_links.txt
src/nexradutils.egg-info/requires.txt
src/nexradutils.egg-info/top_level.txt
src/nexradutils/data/n0q.wld
src/nexradutils/tests/__init__.py
src/nexradutils/tests/nexrad2018-01-01T00-00-00.png
src/nexradutils/tests/test_mod.py
src/nexradutils/tests/test_scripts.py