Metadata-Version: 2.1
Name: nexradutils
Version: 1.0.0
Summary: easily download and plot NEXRAD weather radar reflectivity data
Home-page: https://github.com/space-physics/nexradutils
Author: Michael Hirsch, Ph.D.
Author-email: scivision@users.noreply.github.com
License: UNKNOWN
Keywords: nexrad,weather radar
Platform: UNKNOWN
Classifier: Development Status :: 5 - Production/Stable
Classifier: Environment :: Console
Classifier: Intended Audience :: Science/Research
Classifier: Operating System :: OS Independent
Classifier: Programming Language :: Python :: 3
Classifier: Topic :: Scientific/Engineering :: Atmospheric Science
Requires-Python: >=3.7
Provides-Extra: tests
Provides-Extra: plots
